shaper_format/__init__.py
shaper_format/core.py
shaper_format-1.1.3.dist-info/licenses/LICENSE
shaper_format-1.1.3.dist-info/METADATA
shaper_format-1.1.3.dist-info/WHEEL
shaper_format-1.1.3.dist-info/top_level.txt
shaper_format-1.1.3.dist-info/RECORD
