Metadata-Version: 2.4
Name: shaper_format
Version: 1.1.3
Summary: Tools to convert data into the format needed for Stateshaper. Stateshaper is a package that derives infinite memory from only a few bytes.
Author-email: "Jason G. Dunn" <jasongdunn@outlook.com>
License: MIT License
Project-URL: Homepage, https://github.com/jgddesigns/stateshaper/tree/shaper_format
Requires-Python: >=3.10
License-File: LICENSE
Dynamic: license-file
